combinido_crud_app/__init__.py
combinido_crud_app/main.py
combinido_crud_app-0.4.0.dist-info/METADATA
combinido_crud_app-0.4.0.dist-info/WHEEL
combinido_crud_app-0.4.0.dist-info/entry_points.txt
combinido_crud_app-0.4.0.dist-info/top_level.txt
combinido_crud_app-0.4.0.dist-info/RECORD
