Metadata-Version: 2.1
Name: combinido_crud_app
Version: 0.4.0
Summary: A simple database CRUD application with SQLite and TKinter
Home-page: 
Author: Rico Combinido
Author-email: ricocombinido9@gmail.com
Classifier: Programming Language :: Python :: 3
Classifier: License :: OSI Approved :: MIT License
Classifier: Operating System :: OS Independent
Requires-Python: >=3.6
Requires-Dist: ttkbootstrap
